{"reports":[{"gameId":448,"title":"Scores for 2010-11-16.","playerScores":[{"name":"Greg Matthews","score":13},{"name":"Charles Fastner","score":9},{"name":"Blake Adams","score":4},{"name":"Tony Roberts","score":3},{"name":"Jeremy Stangel","score":-10},{"name":"Brian Echtner","score":-19}],"pointSpread":29},{"gameId":449,"title":"Scores for 2010-11-12.","playerScores":[{"name":"Greg Matthews","score":16},{"name":"Tony Roberts","score":7},{"name":"Blake Adams","score":6},{"name":"Rob Berken","score":-10},{"name":"Jeremy Stangel","score":-19}],"pointSpread":29},{"gameId":450,"title":"Scores for 2010-11-11.","playerScores":[{"name":"Jeremy Stangel","score":25},{"name":"Greg Matthews","score":16},{"name":"Blake Adams","score":-4},{"name":"Dave Peters","score":-10},{"name":"Tony Roberts","score":-27}],"pointSpread":41},{"gameId":451,"title":"Scores for 2010-11-09.","playerScores":[{"name":"Greg Matthews","score":25},{"name":"Blake Adams","score":10},{"name":"Jeremy Stangel","score":2},{"name":"Brian Echtner","score":-4},{"name":"Rob Berken","score":-9},{"name":"Tony Roberts","score":-24}],"pointSpread":37},{"gameId":452,"title":"Scores for 2010-11-05.","playerScores":[{"name":"Brian Echtner","score":18},{"name":"Blake Adams","score":14},{"name":"Rob Berken","score":4},{"name":"Jacob Buysse","score":-13},{"name":"Greg Matthews","score":-23}],"pointSpread":36},{"gameId":453,"title":"Scores for 2010-11-04.","playerScores":[{"name":"Greg Matthews","score":11},{"name":"Charles Fastner","score":5},{"name":"Brian Echtner","score":3},{"name":"Dave Peters","score":3},{"name":"Rob Berken","score":-1},{"name":"Blake Adams","score":-21}],"pointSpread":22},{"gameId":454,"title":"Scores for 2010-11-03.","playerScores":[{"name":"Charles Fastner","score":23},{"name":"Tony Roberts","score":12},{"name":"Jacob Buysse","score":0},{"name":"Greg Matthews","score":-7},{"name":"Blake Adams","score":-12},{"name":"Brian Echtner","score":-16}],"pointSpread":35},{"gameId":455,"title":"Scores for 2010-11-02.","playerScores":[{"name":"Rob Berken","score":14},{"name":"Blake Adams","score":11},{"name":"Brian Echtner","score":10},{"name":"Greg Matthews","score":-12},{"name":"Tony Roberts","score":-23}],"pointSpread":35},{"gameId":456,"title":"Scores for 2010-10-29.","playerScores":[{"name":"Charles Fastner","score":22},{"name":"Blake Adams","score":13},{"name":"Mark Centgraf","score":-5},{"name":"Rob Berken","score":-9},{"name":"Jacob Buysse","score":-21}],"pointSpread":35},{"gameId":457,"title":"Scores for 2010-10-28.","playerScores":[{"name":"Rob Berken","score":22},{"name":"Greg Matthews","score":8},{"name":"Blake Adams","score":5},{"name":"Tony Roberts","score":2},{"name":"Brian Echtner","score":-13},{"name":"Tracy Mueller","score":-24}],"pointSpread":37}]}